{"edges":[[0,1],[1,2],[0,2],[0,2],[2,3],[2,3],[2,3],[1,3],[2,3],[3,4],[3,4]],"nodes":[{"is_barrier":false,"is_compute":false,"is_load":true,"is_store":false,"is_vector":false,"opcode":4891},{"is_barrier":false,"is_compute":false,"is_load":true,"is_store":false,"is_vector":false,"opcode":10153},{"is_barrier":false,"is_compute":false,"is_load":true,"is_store":false,"is_vector":false,"opcode":10449},{"is_barrier":false,"is_compute":false,"is_load":true,"is_store":false,"is_vector":false,"opcode":6459},{"is_barrier":false,"is_compute":true,"is_load":false,"is_store":false,"is_vector":false,"opcode":5394}]}