{"edges":[[1,2],[2,3],[3,4],[3,4],[0,5],[0,5],[0,5],[4,6],[6,7]],"nodes":[{"is_barrier":false,"is_compute":false,"is_load":true,"is_store":false,"is_vector":false,"opcode":1952},{"is_barrier":false,"is_compute":false,"is_load":false,"is_store":false,"is_vector":false,"opcode":1814},{"is_barrier":false,"is_compute":true,"is_load":false,"is_store":false,"is_vector":false,"opcode":2951},{"is_barrier":false,"is_compute":true,"is_load":false,"is_store":false,"is_vector":false,"opcode":804},{"is_barrier":false,"is_compute":true,"is_load":false,"is_store":false,"is_vector":false,"opcode":728},{"is_barrier":false,"is_compute":false,"is_load":true,"is_store":false,"is_vector":false,"opcode":427},{"is_barrier":false,"is_compute":true,"is_load":false,"is_store":false,"is_vector":false,"opcode":1955},{"is_barrier":false,"is_compute":true,"is_load":false,"is_store":false,"is_vector":false,"opcode":811}],"source":"\tmovslq\t32(%r12), %rdx\n\tmovl\t$4096, %r8d\n\tsubl\t%edx, %r8d\n\tcmpl\t%r14d, %r8d\n\tcmovgl\t%r14d, %r8d\n\taddq\t56(%r12), %rdx\n\tmovslq\t%r8d, %rax\n\tcmpq\t$8, %rax\n"}