{"edges":[[1,2],[2,3],[2,3],[1,3],[3,4],[0,5]],"nodes":[{"is_barrier":false,"is_compute":true,"is_load":false,"is_store":false,"is_vector":false,"opcode":17767},{"is_barrier":false,"is_compute":true,"is_load":false,"is_store":false,"is_vector":false,"opcode":1398},{"is_barrier":false,"is_compute":true,"is_load":false,"is_store":false,"is_vector":false,"opcode":2042},{"is_barrier":false,"is_compute":false,"is_load":true,"is_store":false,"is_vector":false,"opcode":418},{"is_barrier":false,"is_compute":true,"is_load":false,"is_store":false,"is_vector":false,"opcode":426},{"is_barrier":false,"is_compute":true,"is_load":false,"is_store":false,"is_vector":false,"opcode":804}],"source":"\txorl\t%eax, %eax\n\tleaq\t32(%rsp), %rdx\n\tnopl\t(%rax,%rax)\n\taddl\t(%rdx,%rax), %r15d\n\taddq\t$4, %rax\n\tcmpl\t%eax, %ecx\n"}