{"edges":[[1,2],[2,3],[1,3],[1,3],[1,4],[2,4],[3,5],[2,5],[4,5],[5,6],[3,6],[5,7],[3,7],[3,7],[6,7],[7,8],[6,8],[4,8],[8,9],[5,9],[8,9],[9,10],[7,10],[8,11],[10,11],[11,12],[9,13],[7,13],[13,14],[14,15]],"nodes":[{"is_barrier":false,"is_compute":true,"is_load":false,"is_store":false,"is_vector":false,"opcode":2041},{"is_barrier":false,"is_compute":false,"is_load":true,"is_store":false,"is_vector":false,"opcode":1952},{"is_barrier":false,"is_compute":false,"is_load":true,"is_store":false,"is_vector":false,"opcode":1952},{"is_barrier":false,"is_compute":false,"is_load":true,"is_store":false,"is_vector":false,"opcode":1952},{"is_barrier":false,"is_compute":true,"is_load":false,"is_store":false,"is_vector":false,"opcode":1192},{"is_barrier":false,"is_compute":false,"is_load":true,"is_store":false,"is_vector":false,"opcode":1952},{"is_barrier":false,"is_compute":true,"is_load":false,"is_store":false,"is_vector":false,"opcode":1192},{"is_barrier":false,"is_compute":false,"is_load":true,"is_store":false,"is_vector":false,"opcode":1952},{"is_barrier":false,"is_compute":true,"is_load":false,"is_store":false,"is_vector":false,"opcode":1398},{"is_barrier":false,"is_compute":false,"is_load":true,"is_store":false,"is_vector":false,"opcode":1952},{"is_barrier":false,"is_compute":true,"is_load":false,"is_store":false,"is_vector":false,"opcode":1192},{"is_barrier":false,"is_compute":true,"is_load":false,"is_store":false,"is_vector":false,"opcode":428},{"is_barrier":false,"is_compute":true,"is_load":false,"is_store":false,"is_vector":false,"opcode":2705},{"is_barrier":false,"is_compute":false,"is_load":true,"is_store":true,"is_vector":false,"opcode":415},{"is_barrier":false,"is_compute":true,"is_load":false,"is_store":false,"is_vector":false,"opcode":426},{"is_barrier":false,"is_compute":true,"is_load":false,"is_store":false,"is_vector":false,"opcode":813}],"source":"\tnop\n\tmovslq\t-4(%rcx,%rdx,4), %rdi\n\tmovslq\t20(%rax), %r9\n\tmovslq\t(%rcx,%rdx,4), %r10\n\timulq\t%rdi, %r9\n\tmovslq\t24(%rax), %rdi\n\timulq\t%r10, %rdi\n\tmovslq\t4(%rcx,%rdx,4), %r10\n\tleaq\t64(%r9,%rdi), %rdi\n\tmovslq\t28(%rax), %r9\n\timulq\t%r10, %r9\n\taddq\t%r9, %rdi\n\tsarq\t$7, %rdi\n\taddl\t%edi, (%rsi,%rdx,4)\n\taddq\t$1, %rdx\n\tcmpq\t%rdx, %r11\n"}