{"edges":[[0,1],[1,2],[1,2],[2,3],[2,3],[3,4],[3,4],[4,5],[5,6],[0,7],[6,7],[0,7],[6,8],[7,9],[8,9],[7,10],[4,11],[3,11],[5,11],[9,12],[11,13],[11,13],[2,13]],"nodes":[{"is_barrier":false,"is_compute":false,"is_load":true,"is_store":false,"is_vector":false,"opcode":1919},{"is_barrier":false,"is_compute":true,"is_load":false,"is_store":false,"is_vector":false,"opcode":1997},{"is_barrier":false,"is_compute":true,"is_load":false,"is_store":false,"is_vector":false,"opcode":448},{"is_barrier":false,"is_compute":true,"is_load":false,"is_store":false,"is_vector":false,"opcode":906},{"is_barrier":false,"is_compute":true,"is_load":false,"is_store":false,"is_vector":false,"opcode":930},{"is_barrier":false,"is_compute":true,"is_load":false,"is_store":false,"is_vector":false,"opcode":910},{"is_barrier":false,"is_compute":false,"is_load":false,"is_store":false,"is_vector":false,"opcode":1817},{"is_barrier":false,"is_compute":false,"is_load":false,"is_store":true,"is_vector":false,"opcode":1808},{"is_barrier":false,"is_compute":true,"is_load":false,"is_store":false,"is_vector":false,"opcode":2036},{"is_barrier":false,"is_compute":true,"is_load":false,"is_store":false,"is_vector":false,"opcode":728},{"is_barrier":false,"is_compute":true,"is_load":false,"is_store":false,"is_vector":false,"opcode":1210},{"is_barrier":false,"is_compute":true,"is_load":false,"is_store":false,"is_vector":false,"opcode":2996},{"is_barrier":false,"is_compute":true,"is_load":false,"is_store":false,"is_vector":false,"opcode":419},{"is_barrier":false,"is_compute":true,"is_load":false,"is_store":false,"is_vector":false,"opcode":448}],"source":"\tmovsd\t16216(%r10,%rcx,8), %xmm0\n\tmulsd\t%xmm2, %xmm0\n\taddsd\t%xmm1, %xmm0\n\tcvtsd2ss\t%xmm0, %xmm3\n\tcvtss2si\t%xmm3, %rax\n\tcvtsi2sd\t%eax, %xmm3\n\tmovl\t%eax, %r14d\n\tmovl\t%eax, (%r13,%rcx,4)\n\tnegl\t%r14d\n\tcmovnsl\t%r14d, %eax\n\tincq\t%rcx\n\tsubsd\t%xmm3, %xmm0\n\taddl\t%eax, %edi\n\taddsd\t%xmm0, %xmm1\n"}