{"edges":[[0,2],[2,3],[3,4],[3,4],[4,5],[2,5],[1,7],[5,7],[1,7]],"nodes":[{"is_barrier":false,"is_compute":false,"is_load":false,"is_store":false,"is_vector":false,"opcode":1817},{"is_barrier":false,"is_compute":false,"is_load":true,"is_store":false,"is_vector":false,"opcode":1816},{"is_barrier":false,"is_compute":true,"is_load":false,"is_store":false,"is_vector":false,"opcode":2951},{"is_barrier":false,"is_compute":true,"is_load":false,"is_store":false,"is_vector":false,"opcode":804},{"is_barrier":false,"is_compute":true,"is_load":false,"is_store":false,"is_vector":false,"opcode":728},{"is_barrier":false,"is_compute":true,"is_load":false,"is_store":false,"is_vector":false,"opcode":419},{"is_barrier":false,"is_compute":true,"is_load":false,"is_store":false,"is_vector":false,"opcode":3069},{"is_barrier":false,"is_compute":false,"is_load":false,"is_store":true,"is_vector":false,"opcode":1808}],"source":"\tmovl\t%r15d, %esi\n\tmovl\t16(%rsp), %ecx\n\tsubl\t%edx, %esi\n\tcmpl\t%eax, %esi\n\tcmovlel\t%esi, %eax\n\taddl\t%edx, %eax\n\ttestl\t%r10d, %r10d\n\tmovl\t%eax, 208(%rsp)\n"}