{"edges":[[0,5],[5,6],[6,7],[7,8],[8,9],[7,10],[9,11],[11,13]],"nodes":[{"is_barrier":false,"is_compute":true,"is_load":false,"is_store":false,"is_vector":false,"opcode":2042},{"is_barrier":false,"is_compute":true,"is_load":false,"is_store":false,"is_vector":false,"opcode":2948},{"is_barrier":false,"is_compute":true,"is_load":false,"is_store":false,"is_vector":false,"opcode":2948},{"is_barrier":false,"is_compute":false,"is_load":false,"is_store":false,"is_vector":false,"opcode":1817},{"is_barrier":false,"is_compute":false,"is_load":false,"is_store":false,"is_vector":false,"opcode":1817},{"is_barrier":false,"is_compute":false,"is_load":false,"is_store":false,"is_vector":false,"opcode":1834},{"is_barrier":false,"is_compute":true,"is_load":false,"is_store":false,"is_vector":false,"opcode":2802},{"is_barrier":false,"is_compute":true,"is_load":false,"is_store":false,"is_vector":false,"opcode":2082},{"is_barrier":false,"is_compute":false,"is_load":false,"is_store":false,"is_vector":false,"opcode":1834},{"is_barrier":false,"is_compute":true,"is_load":false,"is_store":false,"is_vector":false,"opcode":2802},{"is_barrier":false,"is_compute":true,"is_load":false,"is_store":false,"is_vector":false,"opcode":1839},{"is_barrier":false,"is_compute":true,"is_load":false,"is_store":false,"is_vector":false,"opcode":2082},{"is_barrier":false,"is_compute":false,"is_load":false,"is_store":false,"is_vector":false,"opcode":1814},{"is_barrier":false,"is_compute":true,"is_load":false,"is_store":false,"is_vector":false,"opcode":1839}],"source":"\tnopl\t(%rax,%rax)\n\tsubl\t$629145600, %ebx\n\tsubl\t$629145600, %r13d\n\tmovl\t%r12d, %r12d\n\tmovl\t%ebp, %ebp\n\tmovq\t%rbx, %rax\n\tshlq\t$32, %rax\n\torq\t%rax, %r12\n\tmovq\t%r13, %rax\n\tshlq\t$32, %rax\n\tmovq\t%r12, %xmm1\n\torq\t%rax, %rbp\n\tmovl\t$600, %eax\n\tmovq\t%rbp, %xmm3\n"}