{"edges":[[0,2],[2,3],[1,3],[3,4],[3,4]],"nodes":[{"is_barrier":false,"is_compute":false,"is_load":false,"is_store":false,"is_vector":false,"opcode":1817},{"is_barrier":false,"is_compute":false,"is_load":false,"is_store":false,"is_vector":false,"opcode":1814},{"is_barrier":false,"is_compute":true,"is_load":false,"is_store":false,"is_vector":false,"opcode":703},{"is_barrier":false,"is_compute":true,"is_load":false,"is_store":false,"is_vector":false,"opcode":1154},{"is_barrier":false,"is_compute":false,"is_load":false,"is_store":false,"is_vector":false,"opcode":1817}],"source":"\tmovl\t%r12d, %eax\n\tmovl\t$16, %ecx\n\tcltd\n\tidivl\t%ecx\n\tmovl\t%eax, %ecx\n"}