{"edges":[[0,1],[1,2],[1,2],[2,3],[2,3],[3,4],[2,4],[3,4],[4,5],[4,5]],"nodes":[{"is_barrier":false,"is_compute":true,"is_load":false,"is_store":false,"is_vector":false,"opcode":2046},{"is_barrier":false,"is_compute":true,"is_load":false,"is_store":false,"is_vector":false,"opcode":2042},{"is_barrier":false,"is_compute":false,"is_load":true,"is_store":false,"is_vector":false,"opcode":1833},{"is_barrier":false,"is_compute":false,"is_load":true,"is_store":false,"is_vector":false,"opcode":1952},{"is_barrier":false,"is_compute":true,"is_load":false,"is_store":false,"is_vector":false,"opcode":1398},{"is_barrier":false,"is_compute":true,"is_load":false,"is_store":false,"is_vector":false,"opcode":813}],"source":"\tnopw\t%cs:(%rax,%rax)\n\tnopl\t(%rax,%rax)\n\tmovq\t8(%rdi), %rax\n\tmovslq\t16(%rdi), %rdx\n\tleaq\t-32(%rax,%rdx), %rsi\n\tcmpq\t%rsi, %rax\n"}