{"edges":[],"nodes":[{"is_barrier":false,"is_compute":true,"is_load":false,"is_store":false,"is_vector":false,"opcode":17767},{"is_barrier":false,"is_compute":false,"is_load":false,"is_store":false,"is_vector":false,"opcode":1814},{"is_barrier":false,"is_compute":false,"is_load":false,"is_store":false,"is_vector":false,"opcode":1834},{"is_barrier":false,"is_compute":false,"is_load":false,"is_store":false,"is_vector":false,"opcode":1817}],"source":"\txorl\t%esi, %esi\n\tmovl\t$1, %edx\n\tmovq\t%rbp, %rdi\n\tmovl\t%eax, %ebx\n"}