{"edges":[[0,1],[0,1],[1,4],[4,5],[0,5],[5,6],[1,6],[5,7]],"nodes":[{"is_barrier":false,"is_compute":false,"is_load":true,"is_store":false,"is_vector":false,"opcode":1833},{"is_barrier":false,"is_compute":false,"is_load":true,"is_store":false,"is_vector":false,"opcode":1833},{"is_barrier":false,"is_compute":true,"is_load":false,"is_store":false,"is_vector":false,"opcode":17767},{"is_barrier":false,"is_compute":true,"is_load":false,"is_store":false,"is_vector":false,"opcode":2071},{"is_barrier":false,"is_compute":true,"is_load":false,"is_store":false,"is_vector":false,"opcode":1398},{"is_barrier":false,"is_compute":false,"is_load":true,"is_store":false,"is_vector":false,"opcode":1833},{"is_barrier":false,"is_compute":false,"is_load":false,"is_store":true,"is_vector":false,"opcode":1825},{"is_barrier":false,"is_compute":false,"is_load":false,"is_store":false,"is_vector":false,"opcode":1834}],"source":"\tmovq\t(%rsp), %rax\n\tmovq\t48(%rsp), %rdx\n\txorl\t%ecx, %ecx\n\torl\t$-1, %esi\n\tleaq\t-12802(%rip), %r8\n\tmovq\t8(%rax), %rbx\n\tmovq\t$0, 176(%rsp)\n\tmovq\t%rbx, %rdi\n"}